dsvenv/.version
dsvenv/__init__.py
dsvenv/__main__.py
dsvenv/main.py
dsvenv-3.2.2.dist-info/METADATA
dsvenv-3.2.2.dist-info/WHEEL
dsvenv-3.2.2.dist-info/entry_points.txt
dsvenv-3.2.2.dist-info/top_level.txt
dsvenv-3.2.2.dist-info/RECORD
