Metadata-Version: 2.4
Name: dsvenv
Version: 3.2.2
Summary: Utility to create and initialize a virtual environment based on a `requirements.txt` file.
Home-page: 
Author: DS
Author-email: grazhopper+pypi@gmail.com
Requires-Python: >=3.10
Requires-Dist: packaging
Requires-Dist: uv
Dynamic: author
Dynamic: author-email
Dynamic: description-content-type
Dynamic: requires-dist
Dynamic: requires-python
Dynamic: summary
